{
  "project_info": {
    "project_number": "733014771219",
    "project_id": "othello-94686",
    "storage_bucket": "othello-94686.appspot.com"
  },
  "client": [
    {
      "client_info": {
        "mobilesdk_app_id": "1:733014771219:android:c750d7cde13d0a78f9a1e6",
        "android_client_info": {
          "package_name": "com.vishnuworld.othello"
        }
      },
      "oauth_client": [
        {
          "client_id": "733014771219-9iqdeg1o7kt834dp13a89fos5vc9g89k.apps.googleusercontent.com",
          "client_type": 3
        }
      ],
      "api_key": [
        {
          "current_key": "AIzaSyB4uVDXNu89GExfEWpD7131h3yAMhnjdLE"
        }
      ],
      "services": {
        "appinvite_service": {
          "other_platform_oauth_client": [
            {
              "client_id": "733014771219-9iqdeg1o7kt834dp13a89fos5vc9g89k.apps.googleusercontent.com",
              "client_type": 3
            }
          ]
        }
      }
    }
  ],
  "configuration_version": "1"
}